<?xml version="1.0" encoding="UTF-8"?>
<person>
    <id>101446</id>
    <authorities>
        <authority service="viaf"/>
    </authorities>
    <names>
        <preferred>
            <name>Bloxham, William Dunnington</name>
        </preferred>
        <alternates/>
        <originals variants="2">
            <original source-urls="1">
                <name>Bloxham, William Dunnington</name>
                <source-url>https://history.state.gov/departmenthistory/people/bloxham-william-dunnington</source-url>
            </original>
            <original source-urls="1">
                <name>William D. Bloxham</name>
                <source-url>https://history.state.gov/departmenthistory/people/bloxham-william-dunnington</source-url>
            </original>
        </originals>
        <titles-from-name variants="0"/>
    </names>
    <birth-year>1835</birth-year>
    <death-year>1911</death-year>
    <remarks variants="1">
        <remark source-urls="1">
            <p>Non-career appointee. Minister Resident/Consul General (Bolivia).</p>
            <source-url>https://history.state.gov/departmenthistory/people/bloxham-william-dunnington</source-url>
        </remark>
    </remarks>
</person>