<?xml version="1.0" encoding="UTF-8"?>
<person>
    <id>108835</id>
    <authorities>
        <authority service="viaf"/>
    </authorities>
    <names>
        <preferred>
            <name>McDowell, William Wallace</name>
        </preferred>
        <alternates/>
        <originals variants="2">
            <original source-urls="1">
                <name>McDowell, William Wallace</name>
                <source-url>https://history.state.gov/departmenthistory/people/mcdowell-william-wallace</source-url>
            </original>
            <original source-urls="1">
                <name>W.W. McDowell</name>
                <source-url>https://history.state.gov/departmenthistory/people/mcdowell-william-wallace</source-url>
            </original>
        </originals>
        <titles-from-name variants="0"/>
    </names>
    <birth-year>1867</birth-year>
    <death-year>1934</death-year>
    <remarks variants="1">
        <remark source-urls="1">
            <p>Non-career appointee. Envoy Extraordinary and Minister Plenipotentiary (Ireland).</p>
            <source-url>https://history.state.gov/departmenthistory/people/mcdowell-william-wallace</source-url>
        </remark>
    </remarks>
</person>