<?xml version="1.0" encoding="UTF-8"?>
<person>
    <id>114783</id>
    <authorities>
        <authority service="viaf"/>
    </authorities>
    <names>
        <preferred>
            <name>Wood, Walter A., Jr.</name>
        </preferred>
        <alternates/>
        <originals variants="1">
            <original source-urls="1">
                <name>Wood, Major General Walter A., Jr.</name>
                <source-url>https://history.state.gov/historicaldocuments/frus1945Malta/persons#p_W6</source-url>
            </original>
        </originals>
        <titles-from-name variants="1">
            <title source-urls="1">
                <name>Major General</name>
                <source-url>https://history.state.gov/historicaldocuments/frus1945Malta/persons#p_W6</source-url>
            </title>
        </titles-from-name>
    </names>
    <birth-year/>
    <death-year/>
    <remarks variants="1">
        <remark source-urls="1">
            <p>U. S. A., Deputy Director of Plans and Operations, Headquarters, Army Service Forces, and member of the Joint Logistics Committee of the Joint Chiefs of Staff.</p>
            <source-url>https://history.state.gov/historicaldocuments/frus1945Malta/persons#p_W6</source-url>
        </remark>
    </remarks>
</person>