<?xml version="1.0" encoding="UTF-8"?>
<person>
    <id>111429</id>
    <authorities>
        <authority service="viaf"/>
    </authorities>
    <names>
        <preferred>
            <name>Robb, James</name>
        </preferred>
        <alternates/>
        <originals variants="1">
            <original source-urls="1">
                <name>Robb, Air Marshal Sir James</name>
                <source-url>https://history.state.gov/historicaldocuments/frus1945Malta/persons#p_R3</source-url>
            </original>
        </originals>
        <titles-from-name variants="1">
            <title source-urls="1">
                <name>Air Marshal Sir</name>
                <source-url>https://history.state.gov/historicaldocuments/frus1945Malta/persons#p_R3</source-url>
            </title>
        </titles-from-name>
    </names>
    <birth-year/>
    <death-year/>
    <remarks variants="1">
        <remark source-urls="1">
            <p>Deputy Chief of Staff (Air), Supreme Headquarters, Allied Expeditionary Force.</p>
            <source-url>https://history.state.gov/historicaldocuments/frus1945Malta/persons#p_R3</source-url>
        </remark>
    </remarks>
</person>