<?xml version="1.0" encoding="UTF-8"?>
<person>
    <id>101629</id>
    <authorities>
        <authority service="viaf"/>
    </authorities>
    <names>
        <preferred>
            <name>Bowie, Barbara</name>
        </preferred>
        <alternates/>
        <originals variants="1">
            <original source-urls="1">
                <name>Bowie, Barbara</name>
                <source-url>https://history.state.gov/historicaldocuments/frus1977-80v02/persons#p_BB_2</source-url>
            </original>
        </originals>
        <titles-from-name variants="0"/>
    </names>
    <birth-year/>
    <death-year/>
    <remarks variants="1">
        <remark source-urls="1">
            <p>Economics, International Financial Institutions, and Central America, Office of Human Rights, Bureau of Human Rights and Humanitarian Affairs, Department of State, from 1979</p>
            <source-url>https://history.state.gov/historicaldocuments/frus1977-80v02/persons#p_BB_2</source-url>
        </remark>
    </remarks>
</person>