<?xml version="1.0" encoding="UTF-8"?>
<person>
    <id>109081</id>
    <authorities>
        <authority service="viaf"/>
    </authorities>
    <names>
        <preferred>
            <name>Metcalf, Lee Warren</name>
        </preferred>
        <alternates/>
        <originals variants="1">
            <original source-urls="2">
                <name>Metcalf, Lee Warren</name>
                <source-url>https://history.state.gov/historicaldocuments/frus1969-76ve01/persons#p_MLW1</source-url>
                <source-url>https://history.state.gov/historicaldocuments/frus1969-76ve03/persons#p_MLW1</source-url>
            </original>
        </originals>
        <titles-from-name variants="0"/>
    </names>
    <birth-year/>
    <death-year/>
    <remarks variants="2">
        <remark source-urls="1">
            <p>Senator (D–Montana), Member, Senate Subcommittee on Outer Continental Shelf, Senate Interior and Insular Affairs Committee</p>
            <source-url>https://history.state.gov/historicaldocuments/frus1969-76ve01/persons#p_MLW1</source-url>
        </remark>
        <remark source-urls="1">
            <p>Democratic Senator from Montana, Chairman, Minerals, Materials and Fuels Subcommittee, Interior and Insular Affairs Committee, U.S. Senate</p>
            <source-url>https://history.state.gov/historicaldocuments/frus1969-76ve03/persons#p_MLW1</source-url>
        </remark>
    </remarks>
</person>