<?xml version="1.0" encoding="UTF-8"?>
<person>
    <id>114355</id>
    <authorities>
        <authority service="viaf"/>
    </authorities>
    <names>
        <preferred>
            <name>Webb, James Watson</name>
        </preferred>
        <alternates/>
        <originals variants="1">
            <original source-urls="1">
                <name>Webb, James Watson</name>
                <source-url>https://history.state.gov/departmenthistory/people/webb-james-watson</source-url>
            </original>
        </originals>
        <titles-from-name variants="0"/>
    </names>
    <birth-year>1802</birth-year>
    <death-year>1884</death-year>
    <remarks variants="1">
        <remark source-urls="1">
            <p>Non-career appointee. Minister Resident (Turkey); Envoy Extraordinary and Minister Plenipotentiary (Brazil); Chargé d'Affaires (Austria).</p>
            <source-url>https://history.state.gov/departmenthistory/people/webb-james-watson</source-url>
        </remark>
    </remarks>
</person>