<?xml version="1.0" encoding="UTF-8"?>
<person>
    <id>103461</id>
    <authorities>
        <authority service="viaf"/>
    </authorities>
    <names>
        <preferred>
            <name>Dichman, Ernest (Ernst Dichmann)</name>
        </preferred>
        <alternates/>
        <originals variants="2">
            <original source-urls="1">
                <name>Dichman, Ernest (Ernst Dichmann)</name>
                <source-url>https://history.state.gov/departmenthistory/people/dichman-ernest-ernst-dichmann</source-url>
            </original>
            <original source-urls="1">
                <name>Ernest Dichman</name>
                <source-url>https://history.state.gov/departmenthistory/people/dichman-ernest-ernst-dichmann</source-url>
            </original>
        </originals>
        <titles-from-name variants="0"/>
    </names>
    <birth-year/>
    <death-year>1885</death-year>
    <remarks variants="1">
        <remark source-urls="1">
            <p>Non-career appointee. Minister Resident (Colombia).</p>
            <source-url>https://history.state.gov/departmenthistory/people/dichman-ernest-ernst-dichmann</source-url>
        </remark>
    </remarks>
</person>