<?xml version="1.0" encoding="UTF-8"?>
<person>
    <id>103695</id>
    <authorities>
        <authority service="viaf"/>
    </authorities>
    <names>
        <preferred>
            <name>Duhalde Vazquez, Alfredo</name>
        </preferred>
        <alternates/>
        <originals variants="1">
            <original source-urls="1">
                <name>Duhalde Vazquez, Alfredo</name>
                <source-url>https://history.state.gov/historicaldocuments/frus1969-76v21/persons#p_DVA_1</source-url>
            </original>
        </originals>
        <titles-from-name variants="0"/>
    </names>
    <birth-year/>
    <death-year/>
    <remarks variants="1">
        <remark source-urls="1">
            <p>Chilean Vice President from September 25, 1945, until June 27, 1946; Acting President from June 27, 1946, until August 3, 1946; Vice President from August 13, 1946, until October 17</p>
            <source-url>https://history.state.gov/historicaldocuments/frus1969-76v21/persons#p_DVA_1</source-url>
        </remark>
    </remarks>
</person>